xml_analysis_framework/__init__.py
xml_analysis_framework/base.py
xml_analysis_framework/base_extended.py
xml_analysis_framework/unified_interface.py
xml_analysis_framework/core/__init__.py
xml_analysis_framework/core/analyzer.py
xml_analysis_framework/core/chunking.py
xml_analysis_framework/core/schema_analyzer.py
xml_analysis_framework/handlers/__init__.py
xml_analysis_framework/handlers/ant_build_handler.py
xml_analysis_framework/handlers/bpmn_handler.py
xml_analysis_framework/handlers/docbook_handler.py
xml_analysis_framework/handlers/enterprise_config_handler.py
xml_analysis_framework/handlers/generic_xml_handler.py
xml_analysis_framework/handlers/gpx_handler.py
xml_analysis_framework/handlers/graphml_handler.py
xml_analysis_framework/handlers/hibernate_handler.py
xml_analysis_framework/handlers/ivy_handler.py
xml_analysis_framework/handlers/kml_handler.py
xml_analysis_framework/handlers/log4j_config_handler.py
xml_analysis_framework/handlers/maven_pom_handler.py
xml_analysis_framework/handlers/openapi_xml_handler.py
xml_analysis_framework/handlers/properties_xml_handler.py
xml_analysis_framework/handlers/rss_handler.py
xml_analysis_framework/handlers/s1000d_entity_handler.py
xml_analysis_framework/handlers/s1000d_handler.py
xml_analysis_framework/handlers/saml_handler.py
xml_analysis_framework/handlers/scap_handler.py
xml_analysis_framework/handlers/servicenow_handler.py
xml_analysis_framework/handlers/sitemap_handler.py
xml_analysis_framework/handlers/soap_envelope_handler.py
xml_analysis_framework/handlers/spring_config_handler.py
xml_analysis_framework/handlers/struts_config_handler.py
xml_analysis_framework/handlers/svg_handler.py
xml_analysis_framework/handlers/test_report_handler.py
xml_analysis_framework/handlers/wadl_handler.py
xml_analysis_framework/handlers/wsdl_handler.py
xml_analysis_framework/handlers/xhtml_handler.py
xml_analysis_framework/handlers/xliff_handler.py
xml_analysis_framework/handlers/xsd_handler.py
xml_analysis_framework-1.4.4.dist-info/licenses/LICENSE
xml_analysis_framework-1.4.4.dist-info/METADATA
xml_analysis_framework-1.4.4.dist-info/WHEEL
xml_analysis_framework-1.4.4.dist-info/entry_points.txt
xml_analysis_framework-1.4.4.dist-info/top_level.txt
xml_analysis_framework-1.4.4.dist-info/RECORD
