Metadata-Version: 2.4
Name: xml-analysis-framework
Version: 1.4.4
Summary: XML document analysis and preprocessing framework designed for AI/ML data pipelines
Home-page: https://github.com/redhat-ai-americas/xml-analysis-framework
Author: Wes Jackson
Author-email: AI Building Blocks <wjackson@redhat.com>
License: MIT
Project-URL: Homepage, https://github.com/redhat-ai-americas/xml-analysis-framework
Project-URL: Repository, https://github.com/redhat-ai-americas/xml-analysis-framework
Project-URL: Issues, https://github.com/redhat-ai-americas/xml-analysis-framework/issues
Project-URL: Documentation, https://github.com/redhat-ai-americas/xml-analysis-framework/blob/main/README.md
Keywords: xml,analysis,ai,ml,document-processing,semantic-search
Classifier: Development Status :: 5 - Production/Stable
Classifier: Intended Audience :: Developers
Classifier: Topic :: Software Development :: Libraries :: Python Modules
Classifier: Topic :: Text Processing :: Markup :: XML
Classifier: License :: OSI Approved :: MIT License
Classifier: Programming Language :: Python :: 3
Classifier: Programming Language :: Python :: 3.8
Classifier: Programming Language :: Python :: 3.9
Classifier: Programming Language :: Python :: 3.10
Classifier: Programming Language :: Python :: 3.11
Classifier: Programming Language :: Python :: 3.12
Requires-Python: >=3.8
License-File: LICENSE
Requires-Dist: defusedxml>=0.7.1
Provides-Extra: dev
Requires-Dist: pytest>=6.0; extra == "dev"
Requires-Dist: black>=21.0; extra == "dev"
Requires-Dist: flake8>=3.8; extra == "dev"
Requires-Dist: mypy>=0.800; extra == "dev"
Provides-Extra: docs
Requires-Dist: sphinx>=3.0; extra == "docs"
Requires-Dist: sphinx_rtd_theme>=0.5; extra == "docs"
Dynamic: author
Dynamic: home-page
Dynamic: license-file
Dynamic: requires-python
